_qlknn_f90wrap.cpython-39-x86_64-linux-gnu.so
qlknnfort.libs/libz-eb09ad1d.so.1.2.3
qlknnfort.libs/libgfortran-2e0d59d6.so.5.0.0
qlknnfort.libs/libquadmath-2d0c479f.so.0.0.0
qlknnfort/hyper.py
qlknnfort/__init__.py
qlknnfort/version.py
qlknnfort/core.py
qlknnfort/qlknn_f90wrap.py
qlknnfort/data/qlknn-hyper-namelists/net_gam_leq_gb.nml
qlknnfort/data/qlknn-hyper-namelists/net_efitem_gb_div_efetem_gb.nml
qlknnfort/data/qlknn-hyper-namelists/net_efeetg_gb.nml
qlknnfort/data/qlknn-hyper-namelists/net_dfitem_gb_div_efetem_gb.nml
qlknnfort/data/qlknn-hyper-namelists/net_efeitg_gb_div_efiitg_gb.nml
qlknnfort/data/qlknn-hyper-namelists/net_vteitg_gb_div_efiitg_gb.nml
qlknnfort/data/qlknn-hyper-namelists/net_dfeitg_gb_div_efiitg_gb.nml
qlknnfort/data/qlknn-hyper-namelists/net_pfetem_gb_div_efetem_gb.nml
qlknnfort/data/qlknn-hyper-namelists/net_efetem_gb.nml
qlknnfort/data/qlknn-hyper-namelists/net_dfiitg_gb_div_efiitg_gb.nml
qlknnfort/data/qlknn-hyper-namelists/net_vtiitg_gb_div_efiitg_gb.nml
qlknnfort/data/qlknn-hyper-namelists/net_vtetem_gb_div_efetem_gb.nml
qlknnfort/data/qlknn-hyper-namelists/net_vcitem_gb_div_efetem_gb.nml
qlknnfort/data/qlknn-hyper-namelists/net_pfeitg_gb_div_efiitg_gb.nml
qlknnfort/data/qlknn-hyper-namelists/net_vcetem_gb_div_efetem_gb.nml
qlknnfort/data/qlknn-hyper-namelists/net_efiitg_gb.nml
qlknnfort/data/qlknn-hyper-namelists/net_vciitg_gb_div_efiitg_gb.nml
qlknnfort/data/qlknn-hyper-namelists/net_vtitem_gb_div_efetem_gb.nml
qlknnfort/data/qlknn-hyper-namelists/net_dfetem_gb_div_efetem_gb.nml
qlknnfort/data/qlknn-hyper-namelists/net_vceitg_gb_div_efiitg_gb.nml
qlknnfort-1.2.0.dist-info/RECORD
qlknnfort-1.2.0.dist-info/COPYING.LESSER
qlknnfort-1.2.0.dist-info/LICENSE
qlknnfort-1.2.0.dist-info/COPYING
qlknnfort-1.2.0.dist-info/WHEEL
qlknnfort-1.2.0.dist-info/METADATA
qlknnfort-1.2.0.dist-info/top_level.txt
