Metadata-Version: 2.1
Name: qlknnfort
Version: 1.2.0
Summary: Pythonic wrappers for the IMAS Access Layer
Home-page: https://gitlab.com/qualikiz-group/QLKNN-fortran
Author: Karel van de Plassche
Author-email: k.l.vandeplassche@differ.nl
Maintainer: Karel van de Plassche
Maintainer-email: k.l.vandeplassche@differ.nl
License: L-GPL
Project-URL: Bug Tracker, https://gitlab.com/qualikiz-group/QLKNN-fortran/-/issues
Project-URL: Documentation, https://qualikiz-group.gitlab.io/QLKNN-fortran/
Project-URL: Source Code, https://gitlab.com/qualikiz-group/QLKNN-fortran
Platform: UNKNOWN
Classifier: Intended Audience :: Science/Research
Classifier: Natural Language :: English
Classifier: Programming Language :: Python :: 3
Classifier: Topic :: Utilities
Requires-Python: >=3.6
Provides-Extra: develop
Provides-Extra: all
